Metadata-Version: 2.1
Name: python-logstash-async2
Version: 2.5.1
Summary: Asynchronous Python logging handler for Logstash.
Home-page: https://github.com/eht16/python-logstash-async
Author: Enrico Tröger
Author-email: enrico.troeger@uvena.de
License: MIT
Project-URL: Source code, https://github.com/eht16/python-logstash-async/
Project-URL: Documentation, https://python-logstash-async.readthedocs.io/en/stable/
Keywords: logging logstash asynchronous
Classifier: Development Status :: 4 - Beta
Classifier: Intended Audience :: Developers
Classifier: License :: OSI Approved :: MIT License
Classifier: Operating System :: OS Independent
Classifier: Programming Language :: Python
Classifier: Programming Language :: Python :: 3
Classifier: Topic :: Internet :: WWW/HTTP
Classifier: Topic :: Software Development :: Libraries :: Python Modules
Classifier: Topic :: System :: Logging
Requires-Python: >3.5
License-File: LICENSE
Requires-Dist: limits
Requires-Dist: pylogbeat
Requires-Dist: requests
